math/__init__.py
math/cnmath.py
mathbycn-0.0.1.dist-info/LICENSE
mathbycn-0.0.1.dist-info/METADATA
mathbycn-0.0.1.dist-info/WHEEL
mathbycn-0.0.1.dist-info/top_level.txt
mathbycn-0.0.1.dist-info/RECORD
