Metadata-Version: 2.1
Name: mathbycn
Version: 0.0.1
Summary: made in china
Home-page: UNKNOWN
Author: cnryh
Author-email: 15543677192@163.com
License: UNKNOWN
Platform: UNKNOWN
Classifier: Programming Language :: Python :: 3
Classifier: License :: OSI Approved :: MIT License
Classifier: Operating System :: OS Independent
Requires-Python: >=3.6
License-File: LICENSE
